odoo/addons/ssi_employee_document_mixin/README.rst
odoo/addons/ssi_employee_document_mixin/__init__.py
odoo/addons/ssi_employee_document_mixin/__manifest__.py
odoo/addons/ssi_employee_document_mixin/models/__init__.py
odoo/addons/ssi_employee_document_mixin/models/mixin_employee_document.py
odoo/addons/ssi_employee_document_mixin/static/description/icon.png
odoo/addons/ssi_employee_document_mixin/templates/employee_document_templates.xml
odoo14_addon_ssi_employee_document_mixin-14.0.4.2.0.dist-info/METADATA
odoo14_addon_ssi_employee_document_mixin-14.0.4.2.0.dist-info/WHEEL
odoo14_addon_ssi_employee_document_mixin-14.0.4.2.0.dist-info/top_level.txt
odoo14_addon_ssi_employee_document_mixin-14.0.4.2.0.dist-info/RECORD
